odoo/addons/mrp_unbuild_restore_origin/README.rst
odoo/addons/mrp_unbuild_restore_origin/__init__.py
odoo/addons/mrp_unbuild_restore_origin/__manifest__.py
odoo/addons/mrp_unbuild_restore_origin/i18n/it.po
odoo/addons/mrp_unbuild_restore_origin/i18n/mrp_unbuild_restore_origin.pot
odoo/addons/mrp_unbuild_restore_origin/models/__init__.py
odoo/addons/mrp_unbuild_restore_origin/models/mrp_unbuild.py
odoo/addons/mrp_unbuild_restore_origin/models/stock_move.py
odoo/addons/mrp_unbuild_restore_origin/readme/CONTRIBUTORS.md
odoo/addons/mrp_unbuild_restore_origin/readme/DESCRIPTION.md
odoo/addons/mrp_unbuild_restore_origin/readme/USAGE.md
odoo/addons/mrp_unbuild_restore_origin/static/description/icon.png
odoo/addons/mrp_unbuild_restore_origin/static/description/index.html
odoo/addons/mrp_unbuild_restore_origin/tests/__init__.py
odoo/addons/mrp_unbuild_restore_origin/tests/test_mrp_unbuild_origin_location.py
odoo/addons/mrp_unbuild_restore_origin/views/mrp_unbuild_views.xml
odoo_addon_mrp_unbuild_restore_origin-16.0.1.1.0.2.dist-info/METADATA
odoo_addon_mrp_unbuild_restore_origin-16.0.1.1.0.2.dist-info/WHEEL
odoo_addon_mrp_unbuild_restore_origin-16.0.1.1.0.2.dist-info/top_level.txt
odoo_addon_mrp_unbuild_restore_origin-16.0.1.1.0.2.dist-info/RECORD
